{
  "file": "doc/pdf_doc2.pdf",
  "summary": "Bu proforma fatura, Ayşe Ünal tarafından sağlanan \"Web İçeriği Yazımı\" hizmeti için düzenlenmiştir. Hizmetin toplam tutarı 2.500,00 TL'dir. KDV ile birlikte genel toplam 2.950,00 TL'dir. Ödeme şekli havale/EFT olarak belirtilmiştir. Hizmet tamamlandığında resmi fatura düzenlenecektir. Ödeme Nora Bank'a yapılacaktır.",
  "text": "Bu belge, sadece teklif amaçlı düzenlenmiş olup, resmi bir fatura yerine geçmez. Hizmet tamamlandıktan sonra resmi fatura düzenlenecektir.Ayşe Ünal Balkan Sok. No:5 Sarıyer/İstanbul 0212 123 24 25 E-posta: merhaba@harikasite.web.tr Vergi Dairesi: Sarıyer VD Vergi No: 9876563218 Ajans Tümer Ilgaz Sok. No:18 Teşvikiye, 34365 İstanbul 0212 123 24 25 E-posta: merhaba@harikasite.web.tr Vergi Dairesi: Şişli VD Vergi No: 4886563236 Ödeme Şekli: Havale/EFT Banka: Nora Bank IBAN: TR12 3456 7890 1234 5678 8001Hizmet Açıklaması Web İçeriği Yazımı 1 1 2.500,00 2.500,00 Miktar Birim Fiyat Toplam Tutar PROFORMA FATURAAra Toplam: 2.500,00 ₺ KDV (%18): 450,00 ₺ Genel Toplam: 2.950,00 ₺Freelance Metin YazarıAYŞE ÜNAL AYŞE ÜNALHİZMETİ ALAN ÖDEME KOŞULLARIHİZMETİ SAĞLAYAN",
  "yake_keywords": [
    "Vergi",
    "İstanbul",
    "E-posta",
    "Dairesi",
    "Sok",
    "Sarıyer",
    "Toplam",
    "belge",
    "geçmez",
    "resmi"
  ],
  "keybert_keywords": [
    "freelance",
    "bank iban",
    "freelance metin",
    "vergi",
    "8001hizmet",
    "bu belge",
    "fiyat toplam",
    "bank",
    "5678 8001hizmet",
    "belge"
  ],
  "structured_keywords": {
    "Tarih": [],
    "Telefon": [
      "0212 123 24 25",
      "1 1 2.500",
      "4886563236",
      "9876563218",
      "12 3456 7890 1234 5678 8001"
    ],
    "Tutar": [
      "2.500,00 ₺",
      "2.950,00 ₺",
      "450,00 ₺"
    ],
    "Şirket Adı": [],
    "Belge Türü": [
      "teklif",
      "FATURA",
      "fatura"
    ],
    "Sektör": []
  },
  "stanza_entities": [
    "Nora Bank IBAN",
    "Sarıyer",
    "Şişli VD Vergi No"
  ],
  "spacy_entities": [
    "Ajans Tümer",
    "TR12",
    "Ilgaz Sok",
    "merhaba@harikasite.web.tr Vergi Dairesi:",
    "Nora Bank",
    "Açıklaması Web İçeriği Yazımı",
    "İstanbul",
    "Ünal Balkan Sok",
    "PROFORMA FATURAAra Toplam",
    "merhaba@harikasite.web.tr Vergi Dairesi",
    "₺",
    "Hizmet",
    "Şişli VD Vergi No"
  ],
  "combined_entities": [
    "Ajans Tümer",
    "TR12",
    "Ilgaz Sok",
    "Sarıyer",
    "merhaba@harikasite.web.tr Vergi Dairesi:",
    "Açıklaması Web İçeriği Yazımı",
    "İstanbul",
    "merhaba@harikasite.web.tr Vergi Dairesi",
    "Ünal Balkan Sok",
    "Nora Bank IBAN",
    "PROFORMA FATURAAra Toplam",
    "Nora Bank",
    "₺",
    "Hizmet",
    "Şişli VD Vergi No"
  ],
  "groq_labels": [
    "Fatura",
    "Ödeme",
    "Vergi"
  ],
  "groq_critical_keywords": [
    "0212 123 24 25",
    "Ayşe Ünal Balkan Sok. No:5 Sarıyer/İstanbul",
    "merhaba@harikasite.web.tr",
    "Sarıyer VD",
    "9876563218",
    "Ajans Tümer Ilgaz Sok. No:18 Teşvikiye, 34365 İstanbul",
    "Şişli VD",
    "4886563236",
    "Nora Bank",
    "TR12 3456 7890 1234 5678 8001",
    "Freelance Metin Yazarı",
    "AYŞE ÜNAL"
  ]
}