{
  "file": "doc/pdf_doc1.pdf",
  "summary": "Ceren Dertsiz adlı şahsın Helin Kınay-Günay İç Tasarım'a düzenlenen fatura detayları aşağıdadır. Fatura No: 002, düzenlenme tarihi 3 Temmuz 2030'dur. Toplam fiyat 8400,00 TL'dir. Ödeme vadesi 3 Temmuz 2030'dur. Faturaya konu olan ürünler arasında mermer, granit, fayans, seramik ve epoksi ürünleri bulunur. Toplam vergi miktarı 5200,00 TL'dir.",
  "text": "8400,00 TL5200,00 TL %15 ÖDEME BİLGİSİ Hesap Adı: CEREN DERTSİZ Hesap No: 123 465 7890 Ödeme Vadesi: 3 Temmuz 2030ARA TOPLAM : VERGİLER : TOPLAM FİYAT :Fatura No: 002 Düzenlenme Tarihi: 3 Temmuz 2030FATURA ALICI BİLGİLERİ Helin Kınay-Günay İç TasarımAtatürk Mah. Gazi Bulvarı No: 12 10100 Karesi/Balıkesir +0 212 123 24 25 merhaba@harikasite.web.tr AÇIKLAMA MİKTAR KDV BİRİM FİYATI TOPLAM MERMER GRANİT FAYANS SERAMİK EPOKSİ25 5 5 1 3100,00 TL 125,00 TL 250,00 TL 150,00 TL 150,00 TL250,00 TL 625,00 TL 125,00 TL 150,00 TL 450,00 TL1 1 1 1 1Atatürk Mah. Gazi Bulvarı No: 12 10100 Karesi/Balıkesir merhaba@harikasite.web.tr *Lorem ipsum dolor sit amet, consectetur adipiscing elit. Curabitur sem orci, faucibus eget turpis sed, euismod egestas arcu. Proin hendrerit bibendum neque vel varius. BİZİ TERCİH ETTİĞİNİZ İÇİN TEŞEKKÜR EDERİZ.",
  "yake_keywords": [
    "Temmuz",
    "Hesap",
    "ÖDEME",
    "TOPLAM",
    "VERGİLER",
    "Mah",
    "Adı",
    "CEREN",
    "Vadesi",
    "FİYAT"
  ],
  "keybert_keywords": [
    "dolor",
    "epoksi",
    "toplam vergi",
    "tl5200 00",
    "karesi balıkesir",
    "vergi",
    "7890",
    "2030fatura alici",
    "temmuz",
    "dolor sit"
  ],
  "structured_keywords": {
    "Tarih": [
      "3 Temmuz 2030"
    ],
    "Telefon": [
      "1 1 1 1 1",
      "25 5 5 1 3100",
      "123 465 7890",
      "+0 212 123 24 25"
    ],
    "Tutar": [
      "125,00 TL",
      "5200,00 TL",
      "625,00 TL",
      "150,00 TL",
      "450,00 TL",
      "3100,00 TL",
      "8400,00 TL",
      "250,00 TL"
    ],
    "Şirket Adı": [],
    "Belge Türü": [
      "Fatura",
      "FATURA"
    ],
    "Sektör": []
  },
  "stanza_entities": [
    "00 TL5200",
    "Proin hendrerit",
    "3 Temmuz",
    "00 TL",
    "Gazi Bulvarı No",
    "00 TL1",
    "Günay İç TasarımAtatürk Mah",
    "Lorem ipsum dolor sit amet",
    "00 TL250",
    "Curabitur",
    "Helin Kınay"
  ],
  "spacy_entities": [
    "Vadesi",
    "KDV BİRİM",
    "Karesi",
    "Gazi Bulvarı",
    "TL1",
    "CEREN",
    "Hesap Adı",
    "TERCİH ETTİĞİNİZ",
    "Balıkesir",
    "Lorem",
    "3 Temmuz 2030FATURA",
    "VERGİLER",
    "BİZİ",
    "ALICI BİLGİLERİ Helin Kınay-Günay İç",
    "TEŞEKKÜR EDERİZ",
    "turpis sed",
    "TL5200,00 TL",
    "MERMER GRANİT",
    "Fatura No"
  ],
  "combined_entities": [
    "Vadesi",
    "Gazi Bulvarı No",
    "KDV BİRİM",
    "Helin Kınay",
    "Karesi",
    "Gazi Bulvarı",
    "TL1",
    "3 Temmuz",
    "CEREN",
    "Hesap Adı",
    "Lorem ipsum dolor sit amet",
    "TERCİH ETTİĞİNİZ",
    "00 TL250",
    "Balıkesir",
    "Proin hendrerit",
    "Lorem",
    "3 Temmuz 2030FATURA",
    "VERGİLER",
    "BİZİ",
    "ALICI BİLGİLERİ Helin Kınay-Günay İç",
    "00 TL5200",
    "TEŞEKKÜR EDERİZ",
    "00 TL",
    "turpis sed",
    "Günay İç TasarımAtatürk Mah",
    "TL5200,00 TL",
    "MERMER GRANİT",
    "Fatura No",
    "Curabitur",
    "00 TL1"
  ],
  "groq_labels": [
    "fatura",
    "ödeme",
    "hesap"
  ],
  "groq_critical_keywords": [
    "8400,00 TL",
    "5200,00 TL",
    "%15",
    "CEREN DERTSİZ",
    "123 465 7890",
    "3 Temmuz 2030",
    "002",
    "Helin Kınay-Günay",
    "İç Tasarım",
    "Atatürk Mah.",
    "Gazi Bulvarı",
    "No: 12",
    "10100",
    "Karesi",
    "Balıkesir",
    "+0 212 123 24 25",
    "merhaba@harikasite.web.tr"
  ]
}